spacestar/__init__.py
spacestar/app.py
spacestar/context.py
spacestar/model.py
spacestar-0.3.3.dist-info/entry_points.txt
spacestar-0.3.3.dist-info/WHEEL
spacestar-0.3.3.dist-info/METADATA
spacestar-0.3.3.dist-info/RECORD
